gemini_model/__init__.py
gemini_model/corrosion/__init__.py
gemini_model/corrosion/co2_corrosion.py
gemini_model/corrosion/co2_corrosion_opt.py
gemini_model/corrosion/correlation/__init__.py
gemini_model/corrosion/correlation/co2_partial_pressure_model.py
gemini_model/corrosion/correlation/dld_model.py
gemini_model/corrosion/correlation/dlm_model.py
gemini_model/corrosion/correlation/norsok_model.py
gemini_model/corrosion/correlations_opt/__init__.py
gemini_model/corrosion/correlations_opt/dld_model_opt.py
gemini_model/corrosion/correlations_opt/dlm_model_opt.py
gemini_model/corrosion/correlations_opt/norsok_model_opt.py
gemini_model/fluid/__init__.py
gemini_model/fluid/pvt_brine.py
gemini_model/fluid/pvt_sim.py
gemini_model/fluid/pvt_water_stp.py
gemini_model/model_abstract.py
gemini_model/pump/__init__.py
gemini_model/pump/esp.py
gemini_model/reservoir/__init__.py
gemini_model/reservoir/inflow_performance.py
gemini_model/reservoir/injectivity_index.py
gemini_model/reservoir/reservoir_pressure_estimation.py
gemini_model/reservoir/reservoir_pressuredrop.py
gemini_model/well/__init__.py
gemini_model/well/annulus_pressure.py
gemini_model/well/correlation/__init__.py
gemini_model/well/correlation/beggsbrill.py
gemini_model/well/correlation/frictiondarcyweisbach.py
gemini_model/well/correlation/hagedronbrown.py
gemini_model/well/correlation/HB_figs.mat
gemini_model/well/correlation/techo.py
gemini_model/well/correlation/temperaturedrop.py
gemini_model/well/pressure_drop.py
gemini_model-0.3.0.dist-info/LICENSE
gemini_model-0.3.0.dist-info/licenses.json
gemini_model-0.3.0.dist-info/METADATA
gemini_model-0.3.0.dist-info/WHEEL
gemini_model-0.3.0.dist-info/RECORD
